[
  {
    "Id": "590c77c6-0398-402a-9171-69a67a5fbf75",
    "Titulo": "Radetzky Marsh",
    "Artista": "Johaan Strauss",
    "Album": "NAN",
    "Ano": 1848
  },
  {
    "Id": "5727e0be-ae34-4935-93c1-e6d567b8ddf5",
    "Titulo": "Alte Kamaraden",
    "Artista": "Carl Teike",
    "Album": "NAN",
    "Ano": 1889
  },
  {
    "Id": "0b535928-6cfa-40ea-aaf9-d03128503703",
    "Titulo": "Preussens Gloria",
    "Artista": "Johann Gottfried",
    "Album": "NAN",
    "Ano": 1871
  },
  {
    "Id": "28859893-0e1d-4345-aad8-48390e0e263d",
    "Titulo": "Fareweel of Slavianka",
    "Artista": "Vasily Agakpin",
    "Album": "NAN",
    "Ano": 1912
  }
]